Metadata-Version: 1.0
Name: dist-gaussbinom
Version: 0.1
Summary: Gaussian and Binomial distributions
Home-page: UNKNOWN
Author: Murali Mohana Krishna Dandu
Author-email: murali.munna94@gmail.com
License: UNKNOWN
Platform: UNKNOWN
